README.rst
setup.py
digital_stopwatch/__init__.py
digital_stopwatch/__main__.py
digital_stopwatch/digital_stopwatch.py
digital_stopwatch.egg-info/PKG-INFO
digital_stopwatch.egg-info/SOURCES.txt
digital_stopwatch.egg-info/dependency_links.txt
digital_stopwatch.egg-info/entry_points.txt
digital_stopwatch.egg-info/top_level.txt